lm_raindrop_integrations/__init__.py
lm_raindrop_integrations/langchain_smartbucket_retriever.py
lm_raindrop_integrations-0.1.6.dist-info/licenses/LICENSE
lm_raindrop_integrations-0.1.6.dist-info/METADATA
lm_raindrop_integrations-0.1.6.dist-info/WHEEL
lm_raindrop_integrations-0.1.6.dist-info/top_level.txt
lm_raindrop_integrations-0.1.6.dist-info/RECORD
