Metadata-Version: 2.4
Name: lm-raindrop-integrations
Version: 0.1.6
Summary: Python SDK for integrating LiquidMetal's Raindrop API with popular frameworks and tools
Home-page: https://github.com/liquidmetal-ai/lm-raindrop-integrations
Author: LiquidMetal
Author-email: LiquidMetal <customer@liquidmetal.ai>
License: MIT
Project-URL: Homepage, https://github.com/liquidmetal-ai/lm-raindrop-integrations
Project-URL: Bug Tracker, https://github.com/liquidmetal-ai/lm-raindrop-integrations/issues
Classifier: Programming Language :: Python :: 3
Classifier: Operating System :: OS Independent
Requires-Python: >=3.8
License-File: LICENSE
Requires-Dist: pydantic>=2.0.0
Requires-Dist: langchain-core>=0.1.0
Requires-Dist: lm-raindrop>=0.1.6
Provides-Extra: langchain
Requires-Dist: langchain-core>=0.1.0; extra == "langchain"
Dynamic: author
Dynamic: home-page
Dynamic: license-file
Dynamic: requires-python
